2020/verilog_divider/divider_2.v
/*  * pipeline_divider.v
    *
    * Divides signed dividend by unsigned divisor.
    * Parameterized to take inputs of variable size.
    *
    * Currently doing long division. Non restoring?
    *
    *
    *
    */

`timescale 1ns/100ps

//numerator = dividend, denominator = divisor
module pipeline_divider (input                             clock,
                         input      [divisor_width - 1:0]  divisor,
                         input      [dividend_width - 1:0] dividend,
                         output reg [dividend_width - 1:0] quotient,
                         output reg [dividend_width - 1:0] remainder);

    //num_width max = 1^, den_width max = 8, number of stages in pipeline
    parameter dividend_width = 16, divisor_width = 8, stages = dividend_width + 1;

    reg [dividend_width + divisor_width - 1:0] divisors   [0:stages];
    reg [dividend_width + divisor_width - 1:0] remainders [0:stages];
    reg [dividend_width - 1:0]                 quotients  [0:stages];

    reg neg_flags [0:stages]; //set if dividend is negative

    always @(posedge clock) begin
        if (dividend[dividend_width - 1] == 1'b1) begin
            neg_flags[0] <= 1'b1;
            remainders[0] <= {{divisor_width{1'b0}}, -dividend};
        end else begin
            neg_flags[0] <= 1'b0;
            remainders[0] <= {{divisor_width{1'b0}}, dividend};
        end
        divisors[0]   <= {divisor, {dividend_width{1'b0}}};
        quotients[0]  <= {dividend_width{1'b0}};
    end

    genvar i;
    generate
        for (i = 0; i < stages; i = i + 1) begin
            always @(posedge clock) begin
                if (remainders[i] - divisors[i] <= remainders[i]) begin //no underflow/positive
                    remainders[i + 1] <= remainders[i] - divisors[i];
                    quotients[i + 1] <= (quotients[i] << 1) | 1;
                end else begin //underflow/negative
                    remainders[i + 1] <= remainders[i];
                    quotients[i + 1] <= quotients[i] << 1;
                end
                divisors[i + 1] <= divisors[i] >> 1;
                neg_flags[i + 1] <= neg_flags[i];
            end
        end
    endgenerate

    //integer j;
    always @(posedge clock) begin
        //for (j = 0; j <= stages; j = j + 1) begin
        //    $display("%b %b %b", divisors[j], quotients[j], remainders[j]);
        //end
        //$display(" ");

        if (neg_flags[stages]) begin
            quotient <= -quotients[stages];
            remainder <= -remainders[stages]; //different size but should be fine
        end else begin
            quotient <= quotients[stages];
            remainder <= remainders[stages];
        end
    end
endmodule

module pipeline_divider_tb();

    reg clock;
    reg [divisor_width_tb - 1:0] divisor;
    reg [dividend_width_tb - 1:0] dividend;

    wire [dividend_width_tb - 1:0] quotient;
    wire [dividend_width_tb - 1:0] remainder;

    parameter dividend_width_tb = 8, divisor_width_tb = 4;

    defparam divider.dividend_width = dividend_width_tb;
    defparam divider.divisor_width = divisor_width_tb;

    pipeline_divider divider(.clock(clock),
                             .divisor(divisor),
                             .dividend(dividend),
                             .quotient(quotient),
                             .remainder(remainder));

    always begin
        clock = 1'b0;
        #500;
        clock = 1'b1;
        #500;
    end

    /*
    integer i,j;
    reg [31:0] rand;
    reg [divisor_width_tb - 1:0] divisor_array [0:dividend_width_tb + 1];
    reg [dividend_width_tb - 1:0] dividend_array [0:dividend_width_tb + 1];
    */
    initial begin
        $dumpfile("pipeline_divider.vcd");
        $dumpvars(0, pipeline_divider_tb);
        /*
        for (i = 0; i < 100; i++) begin
            #500;
            rand = $urandom;
            divisor = rand[31:31 - divisor_width_tb + 1];
            dividend = rand[dividend_width_tb - 1:0];




            for (j = 0; j < dividend_width_tb + 1; j = j + 1) begin

            end


            #500;
        end
        */




                            //quotient, remainder
        #500;
        divisor = 4'b0010;
        dividend = 8'b11101111; //-8,-1
        #1000;
        divisor = 4'b0001;
        dividend = 8'b11101111; //-17,0
        #1000;
        divisor = 4'b0010;
        dividend = 8'b00000111; //3,1
        #1000;
        divisor = 4'b0001;
        dividend = 8'b00001000; //8,0
        #1000;
        divisor = 4'b0001;
        dividend = 8'b00001111; //15,0
        #1000;
        divisor = 4'b0001;
        dividend = 8'b00000111; //7,0
        #1000;
        divisor = 4'b0010;
        dividend = 8'b00000010; //1,0
        #1000;
        divisor = 4'b0010;
        dividend = 8'b00000100; //2,0
        #1000;
        divisor = 4'b0010;
        dividend = 8'b00001111; //7,1
        #1000;
        divisor = 4'b0100;
        dividend = 8'b01010101; //21,1
        #1000;
        divisor = 4'b0011;
        dividend = 8'b01100011; //33,0
        #1000;
        divisor = 4'b0011;
        dividend = 8'b01100100; //33,1
        #1000;
        divisor = 4'd15;
        dividend = 8'd15;       //1,0
        #500;
        #12000;

        $finish;
    end
endmodule

2020/verilog_divider/pipeline_divider.vcd
$date
	Wed Jul 15 12:02:39 2020
$end
$version
	Icarus Verilog
$end
$timescale
	100ps
$end
$scope module pipeline_divider_tb $end
$var wire 8 ! remainder [7:0] $end
$var wire 8 " quotient [7:0] $end
$var reg 1 # clock $end
$var reg 8 $ dividend [7:0] $end
$var reg 4 % divisor [3:0] $end
$scope module divider $end
$var wire 1 # clock $end
$var wire 8 & dividend [7:0] $end
$var wire 4 ' divisor [3:0] $end
$var reg 8 ( quotient [7:0] $end
$var reg 8 ) remainder [7:0] $end
$scope begin genblk1[0] $end
$upscope $end
$scope begin genblk1[1] $end
$upscope $end
$scope begin genblk1[2] $end
$upscope $end
$scope begin genblk1[3] $end
$upscope $end
$scope begin genblk1[4] $end
$upscope $end
$scope begin genblk1[5] $end
$upscope $end
$scope begin genblk1[6] $end
$upscope $end
$scope begin genblk1[7] $end
$upscope $end
$scope begin genblk1[8] $end
$upscope $end
$upscope $end
$upscope $end
$enddefinitions $end
#0
$dumpvars
bx )
bx (
bx '
bx &
bx %
bx $
0#
bx "
bx !
$end
#5000
b11101111 $
b11101111 &
b10 %
b10 '
1#
#10000
0#
#15000
bx0 "
bx0 (
1#
b1 %
b1 '
#20000
0#
#25000
bx00 "
bx00 (
1#
b111 $
b111 &
b10 %
b10 '
#30000
0#
#35000
bx000 "
bx000 (
1#
b1000 $
b1000 &
b1 %
b1 '
#40000
0#
#45000
bx0000 "
bx0000 (
1#
b1111 $
b1111 &
#50000
0#
#55000
bx00000 "
bx00000 (
1#
b111 $
b111 &
#60000
0#
#65000
bx000000 "
bx000000 (
1#
b10 $
b10 &
b10 %
b10 '
#70000
0#
#75000
bx0000000 "
bx0000000 (
1#
b100 $
b100 &
#80000
0#
#85000
b0 "
b0 (
1#
b1111 $
b1111 &
#90000
0#
#95000
1#
b1010101 $
b1010101 &
b100 %
b100 '
#100000
0#
#105000
b11111111 !
b11111111 )
b11111000 "
b11111000 (
1#
b1100011 $
b1100011 &
b11 %
b11 '
#110000
0#
#115000
b0 !
b0 )
b11101111 "
b11101111 (
1#
b1100100 $
b1100100 &
#120000
0#
#125000
b1 !
b1 )
b11 "
b11 (
1#
b1111 $
b1111 &
b1111 %
b1111 '
#130000
0#
#135000
b0 !
b0 )
b1000 "
b1000 (
1#
#140000
0#
#145000
b1111 "
b1111 (
1#
#150000
0#
#155000
b111 "
b111 (
1#
#160000
0#
#165000
b1 "
b1 (
1#
#170000
0#
#175000
b10 "
b10 (
1#
#180000
0#
#185000
b1 !
b1 )
b111 "
b111 (
1#
#190000
0#
#195000
b10101 "
b10101 (
1#
#200000
0#
#205000
b0 !
b0 )
b100001 "
b100001 (
1#
#210000
0#
#215000
b1 !
b1 )
1#
#220000
0#
#225000
b0 !
b0 )
b1 "
b1 (
1#
